pydra/tasks/afni/__init__.py
pydra/tasks/afni/_version.py
pydra/tasks/afni/latest.py
pydra/tasks/afni/v25/__init__.py
pydra/tasks/afni/v25/_post_release.py
pydra/tasks/afni/v25/base.py
pydra/tasks/afni/v25/model/__init__.py
pydra/tasks/afni/v25/model/deconvolve.py
pydra/tasks/afni/v25/model/remlfit.py
pydra/tasks/afni/v25/model/synthesize.py
pydra/tasks/afni/v25/nipype_ports/__init__.py
pydra/tasks/afni/v25/nipype_ports/utils/__init__.py
pydra/tasks/afni/v25/nipype_ports/utils/filemanip.py
pydra/tasks/afni/v25/preprocess/__init__.py
pydra/tasks/afni/v25/preprocess/align_epi_anat_py.py
pydra/tasks/afni/v25/preprocess/allineate.py
pydra/tasks/afni/v25/preprocess/auto_tcorrelate.py
pydra/tasks/afni/v25/preprocess/auto_tlrc.py
pydra/tasks/afni/v25/preprocess/automask.py
pydra/tasks/afni/v25/preprocess/bandpass.py
pydra/tasks/afni/v25/preprocess/blur_in_mask.py
pydra/tasks/afni/v25/preprocess/blur_to_fwhm.py
pydra/tasks/afni/v25/preprocess/clip_level.py
pydra/tasks/afni/v25/preprocess/degree_centrality.py
pydra/tasks/afni/v25/preprocess/despike.py
pydra/tasks/afni/v25/preprocess/detrend.py
pydra/tasks/afni/v25/preprocess/ecm.py
pydra/tasks/afni/v25/preprocess/fim.py
pydra/tasks/afni/v25/preprocess/fourier.py
pydra/tasks/afni/v25/preprocess/hist.py
pydra/tasks/afni/v25/preprocess/lfcd.py
pydra/tasks/afni/v25/preprocess/maskave.py
pydra/tasks/afni/v25/preprocess/means.py
pydra/tasks/afni/v25/preprocess/net_corr.py
pydra/tasks/afni/v25/preprocess/outlier_count.py
pydra/tasks/afni/v25/preprocess/quality_index.py
pydra/tasks/afni/v25/preprocess/qwarp.py
pydra/tasks/afni/v25/preprocess/qwarp_plus_minus.py
pydra/tasks/afni/v25/preprocess/retroicor.py
pydra/tasks/afni/v25/preprocess/roi_stats.py
pydra/tasks/afni/v25/preprocess/seg.py
pydra/tasks/afni/v25/preprocess/skull_strip.py
pydra/tasks/afni/v25/preprocess/t_corr_1d.py
pydra/tasks/afni/v25/preprocess/t_corr_map.py
pydra/tasks/afni/v25/preprocess/t_correlate.py
pydra/tasks/afni/v25/preprocess/t_norm.py
pydra_tasks_afni-0.5.0.dist-info/METADATA
pydra_tasks_afni-0.5.0.dist-info/WHEEL
pydra_tasks_afni-0.5.0.dist-info/licenses/LICENSE
pydra_tasks_afni-0.5.0.dist-info/RECORD
