Metadata-Version: 2.4
Name: pydra-tasks-afni
Version: 0.5.0
Summary: Pydra tasks package for AFNI
Project-URL: Documentation, https://github.com/nipype/pydra-tasks-afni#readme
Project-URL: Issues, https://github.com/nipype/pydra-tasks-afni/issues
Project-URL: Source, https://github.com/nipype/pydra-tasks-afni
Author-email: Nipype developers <neuroimaging@python.org>
Maintainer-email: Nipype developers <neuroimaging@python.org>
License:    Copyright 2021 Nipype developers
License-File: LICENSE
Keywords: MRI,bold,fMRI,neuroimaging,pydra
Classifier: Development Status :: 3 - Alpha
Classifier: Intended Audience :: Science/Research
Classifier: License :: OSI Approved :: Apache Software License
Classifier: Operating System :: OS Independent
Classifier: Programming Language :: Python :: 3
Classifier: Programming Language :: Python :: 3.11
Classifier: Programming Language :: Python :: 3.12
Classifier: Topic :: Scientific/Engineering
Classifier: Topic :: Software Development :: Libraries
Requires-Python: >=3.11
Requires-Dist: fileformats-datascience>=0.3.2
Requires-Dist: fileformats-medimage>=0.10.5
Requires-Dist: fileformats-vendor-afni
Requires-Dist: fileformats>=0.15.4
Requires-Dist: looseversion>=1.3.0
Requires-Dist: pydra>=1.0a2
Provides-Extra: dev
Requires-Dist: black; extra == 'dev'
Requires-Dist: pre-commit; extra == 'dev'
Provides-Extra: test
Requires-Dist: codecov; extra == 'test'
Requires-Dist: fileformats-datascience-extras; extra == 'test'
Requires-Dist: fileformats-extras; extra == 'test'
Requires-Dist: nipype2pydra>=0.5.0; extra == 'test'
Requires-Dist: pluggy>=1.2; extra == 'test'
Requires-Dist: pytest-cov>=4.1.0; extra == 'test'
Requires-Dist: pytest-env; extra == 'test'
Requires-Dist: pytest-rerunfailures; extra == 'test'
Requires-Dist: pytest-xdist>=3.5.0; extra == 'test'
Requires-Dist: pytest>=7.4; extra == 'test'
